hvac_did_flash/__init__.py
hvac_did_flash/__main__.py
hvac_did_flash/auto_program.py
hvac_did_flash/common.py
hvac_did_flash/compatibility.py
hvac_did_flash/config.py
hvac_did_flash/did_flash.py
hvac_did_flash/error_handler.py
hvac_did_flash/file_handler.py
hvac_did_flash/file_scanner.py
hvac_did_flash/firmware_programmer.py
hvac_did_flash/firmware_verifier.py
hvac_did_flash/flash_checker.py
hvac_did_flash/google_drive_helper.py
hvac_did_flash/logger.py
hvac_did_flash/performance_monitor.py
hvac_did_flash/serial_communicator.py
hvac_did_flash/slack_uploader.py
hvac_did_flash/st_link_handler.py
hvac_did_flash/voice_announcer.py
hvac_did_flash-1.2.7.dist-info/licenses/LICENSE
hvac_did_flash-1.2.7.dist-info/METADATA
hvac_did_flash-1.2.7.dist-info/WHEEL
hvac_did_flash-1.2.7.dist-info/entry_points.txt
hvac_did_flash-1.2.7.dist-info/top_level.txt
hvac_did_flash-1.2.7.dist-info/RECORD
