Metadata-Version: 2.4
Name: hvac-did-flash
Version: 1.2.7
Summary: STM32 Firmware Programming System for HVAC devices with DID flash support
Author-email: HVAC Team <team@example.com>
Maintainer-email: HVAC Team <team@example.com>
License-Expression: MIT
Project-URL: Homepage, https://github.com/your-org/hvac-did-flash
Project-URL: Documentation, https://github.com/your-org/hvac-did-flash/blob/main/README.md
Project-URL: Repository, https://github.com/your-org/hvac-did-flash.git
Project-URL: Bug Tracker, https://github.com/your-org/hvac-did-flash/issues
Keywords: STM32,firmware,programming,HVAC,DID,flash
Classifier: Development Status :: 4 - Beta
Classifier: Intended Audience :: Developers
Classifier: Intended Audience :: Manufacturing
Classifier: Operating System :: Microsoft :: Windows
Classifier: Programming Language :: Python :: 3
Classifier: Programming Language :: Python :: 3.8
Classifier: Programming Language :: Python :: 3.9
Classifier: Programming Language :: Python :: 3.10
Classifier: Programming Language :: Python :: 3.11
Classifier: Programming Language :: Python :: 3.12
Classifier: Topic :: Software Development :: Embedded Systems
Classifier: Topic :: System :: Hardware :: Hardware Drivers
Requires-Python: >=3.8
License-File: LICENSE
Requires-Dist: pyserial>=3.5
Requires-Dist: configparser
Requires-Dist: packaging>=25.0
Requires-Dist: psutil>=5.9.0
Requires-Dist: GitPython>=3.1.0
Requires-Dist: slack-sdk>=3.0.0
Requires-Dist: python-dotenv>=0.19.0
Provides-Extra: dev
Requires-Dist: black>=23.3.0; extra == "dev"
Requires-Dist: pylint>=2.17.4; extra == "dev"
Requires-Dist: pytest>=7.3.1; extra == "dev"
Requires-Dist: isort>=5.13.2; extra == "dev"
Dynamic: license-file
